xfinder/__init__.py
xfinder/eval.py
xfinder/examples/__init__.py
xfinder/helpers/__init__.py
xfinder/helpers/data_processing.py
xfinder/helpers/math_evaluator.py
xfinder/helpers/prompt_template.py
xfinder/modules/__init__.py
xfinder/modules/answer_comparator.py
xfinder/modules/answer_extractor.py
xfinder-0.2.6.dist-info/LICENSE
xfinder-0.2.6.dist-info/METADATA
xfinder-0.2.6.dist-info/WHEEL
xfinder-0.2.6.dist-info/entry_points.txt
xfinder-0.2.6.dist-info/top_level.txt
xfinder-0.2.6.dist-info/RECORD
