Metadata-Version: 2.2
Name: xfinder
Version: 0.2.6
Summary: An Robust and Pinpoint Answer Extractor for LLM Evaluation
Author-email: Qingchen Yu <zhgqcyu@gmail.com>
License: Attribution-NonCommercial-NoDerivatives 4.0 International
Project-URL: Repository, https://github.com/IAAR-Shanghai/xFinder
Keywords: LLM,NLP,answer extraction,reliable evaluation
Classifier: Programming Language :: Python :: 3.10
Classifier: Programming Language :: Python :: 3.11
Classifier: Programming Language :: Python :: 3.12
Classifier: Operating System :: OS Independent
Requires-Python: >=3.10
License-File: LICENSE
Requires-Dist: torch==2.3.1
Requires-Dist: transformers>=4.39.0
Requires-Dist: tqdm>=4.65.0
Requires-Dist: huggingface_hub
Requires-Dist: accelerate>=0.26.0
Requires-Dist: tenacity
Requires-Dist: ipywidgets
